{
    "description": "Open-Meteo WMO condition codes and their descriptions in multiple languages.",
    "data": {
        "0": {
            "description": {
                "en": "Sunny",
                "de": "Sonnig",
                "es": "Soleado",
                "fr": "Ensoleillé",
                "it": "Soleggiato"
            }
        },
        "1": {
            "description": {
                "en": "Mainly sunny",
                "de": "Überwiegend sonnig",
                "es": "Principalmente soleado",
                "fr": "Principalement ensoleillé",
                "it": "Prevalentemente soleggiato"
            }
        },
        "2": {
            "description": {
                "en": "Partly cloudy",
                "de": "Teilweise bewölkt",
                "es": "Parcialmente nublado",
                "fr": "Partiellement nuageux",
                "it": "Parzialmente nuvoloso"
            }
        },
        "3": {
            "description": {
                "en": "Overcast",
                "de": "Bewölkt",
                "es": "Nublado",
                "fr": "Nuageux",
                "it": "Coperto"
            }
        },
        "45": {
            "description": {
                "en": "Fog",
                "de": "Nebel",
                "es": "Niebla",
                "fr": "Brouillard",
                "it": "Nebbia"
            }
        },
        "48": {
            "description": {
                "en": "Depositing rime fog",
                "de": "Reifnebel",
                "es": "Niebla con escarcha",
                "fr": "Brouillard givrant",
                "it": "Nebbia con brina"
            }
        },
        "51": {
            "description": {
                "en": "Light drizzle",
                "de": "Leichter Nieselregen",
                "es": "Llovizna ligera",
                "fr": "Bruine légère",
                "it": "Pioviggine leggera"
            }
        },
        "53": {
            "description": {
                "en": "Moderate drizzle",
                "de": "Mäßiger Nieselregen",
                "es": "Llovizna moderada",
                "fr": "Bruine modérée",
                "it": "Pioviggine moderata"
            }
        },
        "55": {
            "description": {
                "en": "Dense drizzle",
                "de": "Starker Nieselregen",
                "es": "Llovizna densa",
                "fr": "Bruine dense",
                "it": "Pioviggine intensa"
            }
        },
        "56": {
            "description": {
                "en": "Light freezing drizzle",
                "de": "Leichter gefrierender Nieselregen",
                "es": "Llovizna helada ligera",
                "fr": "Bruine verglaçante légère",
                "it": "Pioviggine gelata leggera"
            }
        },
        "57": {
            "description": {
                "en": "Dense freezing drizzle",
                "de": "Starker gefrierender Nieselregen",
                "es": "Llovizna helada densa",
                "fr": "Bruine verglaçante dense",
                "it": "Pioviggine gelata intensa"
            }
        },
        "61": {
            "description": {
                "en": "Slight rain",
                "de": "Leichter Regen",
                "es": "Lluvia ligera",
                "fr": "Pluie faible",
                "it": "Pioggia debole"
            }
        },
        "63": {
            "description": {
                "en": "Moderate rain",
                "de": "Mäßiger Regen",
                "es": "Lluvia moderada",
                "fr": "Pluie modérée",
                "it": "Pioggia moderata"
            }
        },
        "65": {
            "description": {
                "en": "Heavy rain",
                "de": "Starker Regen",
                "es": "Lluvia fuerte",
                "fr": "Pluie forte",
                "it": "Pioggia intensa"
            }
        },
        "66": {
            "description": {
                "en": "Light freezing rain",
                "de": "Leichter gefrierender Regen",
                "es": "Lluvia helada ligera",
                "fr": "Pluie verglaçante légère",
                "it": "Pioggia gelata leggera"
            }
        },
        "67": {
            "description": {
                "en": "Heavy freezing rain",
                "de": "Starker gefrierender Regen",
                "es": "Lluvia helada fuerte",
                "fr": "Pluie verglaçante forte",
                "it": "Pioggia gelata intensa"
            }
        },
        "71": {
            "description": {
                "en": "Slight snow fall",
                "de": "Leichter Schneefall",
                "es": "Nevada ligera",
                "fr": "Chute de neige faible",
                "it": "Debole nevicata"
            }
        },
        "73": {
            "description": {
                "en": "Moderate snow fall",
                "de": "Mäßiger Schneefall",
                "es": "Nevada moderada",
                "fr": "Chute de neige modérée",
                "it": "Nevicata moderata"
            }
        },
        "75": {
            "description": {
                "en": "Heavy snow fall",
                "de": "Starker Schneefall",
                "es": "Nevada fuerte",
                "fr": "Chute de neige forte",
                "it": "Forte nevicata"
            }
        },
        "77": {
            "description": {
                "en": "Snow grains",
                "de": "Schneekörner",
                "es": "Granos de nieve",
                "fr": "Grains de neige",
                "it": "Granuli di neve"
            }
        },
        "80": {
            "description": {
                "en": "Slight rain showers",
                "de": "Leichte Regenschauer",
                "es": "Chubascos ligeros",
                "fr": "Averses de pluie faibles",
                "it": "Deboli rovesci di pioggia"
            }
        },
        "81": {
            "description": {
                "en": "Moderate rain showers",
                "de": "Mäßige Regenschauer",
                "es": "Chubascos moderados",
                "fr": "Averses de pluie modérées",
                "it": "Rovesci di pioggia moderati"
            }
        },
        "82": {
            "description": {
                "en": "Violent rain showers",
                "de": "Starke Regenschauer",
                "es": "Chubascos violentos",
                "fr": "Averses de pluie violentes",
                "it": "Forti rovesci di pioggia"
            }
        },
        "85": {
            "description": {
                "en": "Slight snow showers",
                "de": "Leichte Schneeschauer",
                "es": "Chubascos de nieve ligeros",
                "fr": "Averses de neige faibles",
                "it": "Deboli rovesci di neve"
            }
        },
        "86": {
            "description": {
                "en": "Heavy snow showers",
                "de": "Starke Schneeschauer",
                "es": "Chubascos de nieve fuertes",
                "fr": "Averses de neige fortes",
                "it": "Forti rovesci di neve"
            }
        },
        "95": {
            "description": {
                "en": "Slight or moderate thunderstorm",
                "de": "Leichter oder mäßiger Gewitter",
                "es": "Tormenta ligera o moderada",
                "fr": "Orage faible ou modéré",
                "it": "Temporale debole o moderato"
            }
        },
        "96": {
            "description": {
                "en": "Thunderstorm with slight hail",
                "de": "Gewitter mit leichtem Hagel",
                "es": "Tormenta con granizo ligero",
                "fr": "Orage avec grêle faible",
                "it": "Temporale con grandine debole"
            }
        },
        "99": {
            "description": {
                "en": "Thunderstorm with heavy hail",
                "de": "Gewitter mit starkem Hagel",
                "es": "Tormenta con granizo fuerte",
                "fr": "Orage avec forte grêle",
                "it": "Temporale con grandine forte"
            }
        }
    }
}